[
  {
    "id": "d_cera",
    "circleName": "NUEVO",
    "title": "PROMO NOVIEMBRE",
    "subtitle": "Depilación con cera tibia",
    "nroSesiones": "∞",
    "precio": {
      "normal": "$35",
      "promo": "$29.99"
    },
    "btn": {
      "agendar": "#",
      "masInfo": "#"
    },
    "desc": "Piernas completas + bikini brasilero full + estómago + brazos + axilas",
    "data_desc": "PROMO NOVIEMBRE"
  },
  {
    "id": "d_laser",
    "circleName": "NUEVO",
    "title": "AXILAS 2X1",
    "subtitle": "Depilación definitiva",
    "nroSesiones": "8",
    "precio": {
      "normal": "$320",
      "promo": "$160"
    },
    "btn": {
      "agendar": "#",
      "masInfo": "#"
    },
    "desc": "Tratamiento completo de depilacion definitiva de axilas",
    "data_desc": "AXILAS 2X1"
  },
  {
    "id": "d_laser",
    "circleName": "NUEVO",
    "title": "ROSTRO COMPLETO",
    "subtitle": "Depilación definitiva",
    "nroSesiones": "8",
    "precio": {
      "normal": "$160",
      "promo": "$104"
    },
    "btn": {
      "agendar": "#",
      "masInfo": "#"
    },
    "desc": "8 sesiones de $12.99 cada una.",
    "data_desc": "ROSTRO COMPLETO"
  },

  {
    "id": "d_cera",
    "circleName": "NUEVO",
    "title": "2X1 LUNES Y MARTES",
    "subtitle": "Depilación con cera tibia.",
    "nroSesiones": "∞",
    "precio": {
      "normal": "100%",
      "promo": "50% DE DESCUENTO"
    },
    "btn": {
      "agendar": "#",
      "masInfo": "#"
    },
    "desc": "Visítenos con un acompañante los dias lunes y martes y page solo la mitad del valor total.",
    "data_desc": "2X1 LUNES Y MARTES"
  }
]
